haiqv/.env
haiqv/__init__.py
haiqv/api.py
haiqv/client.py
haiqv/binding/__init__.py
haiqv/binding/args_bind.py
haiqv/binding/std_bind.py
haiqv/binding/yaml_bind.py
haiqv/common/__init__.py
haiqv/common/keepalive.py
haiqv/entities/__init__.py
haiqv/entities/experiment.py
haiqv/entities/run.py
haiqv/error/__init__.py
haiqv/error/value_error.py
haiqv/job/__init__.py
haiqv/job/background_task.py
haiqv/job/keepalive_task.py
haiqv/store/__init__.py
haiqv/store/client.py
haiqv/store/log.py
haiqv/store/notebook.py
haiqv/store/run.py
haiqv/utils/__init__.py
haiqv/utils/common.py
haiqv/utils/files.py
haiqv/utils/log_config.py
haiqv-2.0.8.dist-info/METADATA
haiqv-2.0.8.dist-info/WHEEL
haiqv-2.0.8.dist-info/top_level.txt
haiqv-2.0.8.dist-info/RECORD
