Metadata-Version: 2.1
Name: haiqv
Version: 2.0.8
Summary: HAiQV AI Platform SDK for MLOps
Author: haiqv
Author-email: haiqv.ai@hanwha.com
Keywords: haiqv,haiqvml
Classifier: Programming Language :: Python :: 3.8
Classifier: Operating System :: OS Independent
Requires-Python: >=3.8
Requires-Dist: requests
Requires-Dist: python-dotenv
Requires-Dist: pyyaml
Requires-Dist: psutil
Requires-Dist: colorama
Requires-Dist: importlib-metadata
